hwp/__init__.py
hwp/import_python.py
hwp/test_python.py
hwp-0.0.999.dist-info/METADATA
hwp-0.0.999.dist-info/WHEEL
hwp-0.0.999.dist-info/top_level.txt
hwp-0.0.999.dist-info/RECORD
